<?xml version="1.0" encoding="utf-8" ?>
<dwsync>
<file name=".gitignore" server="digital-fury.com//public_html/portfolio/" local="130778366128237227" remote="130785194400000000" />
<file name="bower.json" server="digital-fury.com//public_html/portfolio/" local="130778645149362421" remote="130785194400000000" />
<file name="index.html" server="digital-fury.com//public_html/portfolio/" local="130786967232605929" remote="130787003400000000" />
<file name="npm-debug.log" server="digital-fury.com//public_html/portfolio/" local="130778540526345771" remote="130785195000000000" />
<file name="readme.txt" server="digital-fury.com//public_html/portfolio/" local="130778366128587451" remote="130785195000000000" />
<file name="artwork.html" server="digital-fury.com//public_html/portfolio/" local="130785175763760581" remote="130785212400000000" />
<file name="contact.html" server="digital-fury.com//public_html/portfolio/" local="130785363720592122" remote="130785399600000000" />
<file name="print.html" server="digital-fury.com//public_html/portfolio/" local="130785378168465658" remote="130785414000000000" />
<file name="uidesign.html" server="digital-fury.com//public_html/portfolio/" local="130785361923018176" remote="130785397800000000" />
<file name="favicon.ico" server="digital-fury.com//public_html/portfolio/" local="130785328261049315" remote="130785364800000000" />
</dwsync>